Metadata-Version: 2.1
Name: async-url-validator
Version: 0.9
Summary: Async python package and CLI command for URL validation.
Home-page: http://github.com/cfytrok/async-url-validator
Author: Aleksandr Gavrilov
Author-email: sanya-991@mail.ru
License: MIT
Platform: any
Classifier: Programming Language :: Python :: 3
Classifier: License :: OSI Approved :: MIT License
Classifier: Operating System :: OS Independent
Requires-Python: >=3.5
License-File: LICENSE
